Metadata-Version: 2.1
Name: tap-exacttarget-remove-sud
Version: 1.7.4
Summary: Singer.io tap for extracting data from the ExactTarget API
Home-page: http://fishtownanalytics.com
Author: Fishtown Analytics
License: UNKNOWN
Platform: UNKNOWN
Classifier: Programming Language :: Python :: 3 :: Only
License-File: LICENSE
Requires-Dist: funcy (==1.9.1)
Requires-Dist: singer-python-fork (==5.12.2)
Requires-Dist: python-dateutil (==2.6.0)
Requires-Dist: voluptuous (==0.10.5)
Requires-Dist: Salesforce-FuelSDK-Sans
Provides-Extra: dev
Requires-Dist: ipdb (==0.11) ; extra == 'dev'
Provides-Extra: test
Requires-Dist: pylint (==2.10.2) ; extra == 'test'
Requires-Dist: astroid (==2.7.3) ; extra == 'test'
Requires-Dist: nose ; extra == 'test'
